{
	"format_version": "1.8.0",
	"animations": {
		"animation.dino.walk": {
			"loop": true,
			"animation_length": 0.64,
			"bones": {
				"all1": {
					"rotation": {
						"0.0": [0, 0, 0],
						"0.1667": [0, 0, -5],
						"0.3167": [0, 0, 0],
						"0.4833": [0, 0, 5],
						"0.6333": [0, 0, 0]
					}
				},
				"top": {
					"rotation": {
						"0.0": [-5, 0, 0],
						"0.1667": [10, 0, 0],
						"0.3167": [-5, 0, 0],
						"0.4833": [10, 0, 0],
						"0.6333": [-5, 0, 0]
					},
					"position": {
						"0.0": [0, 0, 0],
						"0.1667": [0, 1, 0],
						"0.3167": [0, 0, 0],
						"0.4833": [0, 1, 0],
						"0.6333": [0, 0, 0]
					}
				},
				"head": {
					"rotation": {
						"0.0": [10, 5, 0],
						"0.1667": [-6, 0, 0],
						"0.3167": [10, -5, 0],
						"0.4833": [-5, 0, 0],
						"0.6333": [10, 5, 0]
					}
				},
				"tail": {
					"rotation": {
						"0.0": [5, 0, -15],
						"0.1667": [-5, 0, 0],
						"0.3167": [5, 0, 15],
						"0.4833": [-5, 0, 0],
						"0.6333": [5, 0, -15]
					}
				},
				"rightleg": {
					"rotation": {
						"0.0": [-45, 0, 0],
						"0.1667": [0, 0, 0],
						"0.3167": [45, 0, 0],
						"0.4833": [21, 0, 0],
						"0.6333": [-45, 0, 0]
					},
					"position": {
						"0.0": [0, 0, 0],
						"0.1667": [0, 0, 0],
						"0.3167": [0, 0, 0],
						"0.4833": [0, 2, 0],
						"0.6333": [0, 0, 0]
					}
				},
				"leftleg": {
					"rotation": {
						"0.0": [45, 0, 0],
						"0.1667": [21, 0, 0],
						"0.3167": [-45, 0, 0],
						"0.4833": [0, 0, 0],
						"0.6333": [45, 0, 0]
					},
					"position": {
						"0.0": [0, 0, 0],
						"0.1667": [0, 2, 0],
						"0.3167": [0, 0, 0],
						"0.4833": [0, 0, 0],
						"0.6333": [0, 0, 0]
					}
				}
			}
		}
	}
}